odoo/addons/project_task_restrict_stage_changes/README.rst
odoo/addons/project_task_restrict_stage_changes/__init__.py
odoo/addons/project_task_restrict_stage_changes/__manifest__.py
odoo/addons/project_task_restrict_stage_changes/i18n/es.po
odoo/addons/project_task_restrict_stage_changes/models/__init__.py
odoo/addons/project_task_restrict_stage_changes/models/project_task.py
odoo/addons/project_task_restrict_stage_changes/models/project_task_type.py
odoo/addons/project_task_restrict_stage_changes/security/project_task_restrict_stage_changes_security.xml
odoo/addons/project_task_restrict_stage_changes/static/description/icon.png
odoo/addons/project_task_restrict_stage_changes/views/project_task_type_views.xml
odoo12_addon_project_task_restrict_stage_changes-12.0.1.0.0.dist-info/METADATA
odoo12_addon_project_task_restrict_stage_changes-12.0.1.0.0.dist-info/WHEEL
odoo12_addon_project_task_restrict_stage_changes-12.0.1.0.0.dist-info/top_level.txt
odoo12_addon_project_task_restrict_stage_changes-12.0.1.0.0.dist-info/RECORD
