Metadata-Version: 2.1
Name: odoo12-addon-project_task_restrict_stage_changes
Version: 12.0.1.0.0
Summary: Configure task stages restricted to a user group
Home-page: https://sygel.es
Author: Sygel
License: AGPL-3
Classifier: Programming Language :: Python
Classifier: Framework :: Odoo
Classifier: Framework :: Odoo :: 12.0
Classifier: License :: OSI Approved :: GNU Affero General Public License v3
Requires-Python: >=3.5
Requires-Dist: odoo<12.1dev,>=12.0a
